requests_sse/__init__.py
requests_sse/client.py
requests_sse-0.4.0.dist-info/LICENSE
requests_sse-0.4.0.dist-info/METADATA
requests_sse-0.4.0.dist-info/WHEEL
requests_sse-0.4.0.dist-info/RECORD
