Metadata-Version: 2.3
Name: requests-sse
Version: 0.4.0
Summary: server-sent events python client library based on requests
Home-page: https://github.com/overcat/requests-sse
License: Apache-2.0
Keywords: server-sent events,sse,stream,requests
Author: overcat
Author-email: 4catcode@gmail.com
Maintainer: overcat
Maintainer-email: 4catcode@gmail.com
Requires-Python: >=3.7,<4.0
Classifier: Development Status :: 4 - Beta
Classifier: Intended Audience :: Developers
Classifier: License :: OSI Approved :: Apache Software License
Classifier: Natural Language :: English
Classifier: Operating System :: OS Independent
Classifier: Programming Language :: Python
Classifier: Programming Language :: Python :: 3
Classifier: Programming Language :: Python :: 3.7
Classifier: Programming Language :: Python :: 3.8
Classifier: Programming Language :: Python :: 3.9
Classifier: Programming Language :: Python :: 3.10
Classifier: Programming Language :: Python :: 3.11
Classifier: Programming Language :: Python :: 3.12
Classifier: Programming Language :: Python :: 3.13
Classifier: Programming Language :: Python :: 3 :: Only
Classifier: Programming Language :: Python :: Implementation :: CPython
Classifier: Programming Language :: Python :: Implementation :: PyPy
Classifier: Topic :: Software Development :: Libraries :: Python Modules
Classifier: Typing :: Typed
Requires-Dist: requests (>=2.0.0,<3.0.0)
Project-URL: Bug Tracker, https://github.com/overcat/requests-sse/issues
Project-URL: Documentation, https://github.com/overcat/requests-sse
Project-URL: Repository, https://github.com/overcat/requests-sse
